LICENSE
MANIFEST.in
README.md
setup.py
prana/__init__.py
prana.egg-info/PKG-INFO
prana.egg-info/SOURCES.txt
prana.egg-info/dependency_links.txt
prana.egg-info/entry_points.txt
prana.egg-info/requires.txt
prana.egg-info/top_level.txt