Metadata-Version: 1.1
Name: prana
Version: 0.0.1
Summary:  Loosely translated Sanskrit word for 'Energy'. Just another interview challenge.
Home-page: https://github.com/dhilipsiva/prana
Author: dhilipsiva
Author-email: dhilipsiva@gmail.com
License: MIT
Keywords: prana dhilipsiva
Platform: UNKNOWN
Classifier: Development Status :: 2 - Pre-Alpha
Classifier: Environment :: Console
Classifier: Intended Audience :: End Users/Desktop
Classifier: License :: OSI Approved :: MIT License
Classifier: Natural Language :: English
Classifier: Operating System :: POSIX
Classifier: Operating System :: Unix
Classifier: Programming Language :: Python
Classifier: Programming Language :: Python :: 3.5
Classifier: Programming Language :: Python :: Implementation :: CPython
Classifier: Topic :: Utilities
